[{"place_id": 256337572, "licence": "Data \u00a9 OpenStreetMap contributors, ODbL 1.0. http://osm.org/copyright", "osm_type": "node", "osm_id": 415937840, "lat": "53.7764297", "lon": "-2.9154693", "class": "amenity", "type": "post_office", "place_rank": 30, "importance": 5.050659952692481e-05, "addresstype": "amenity", "name": "Wrea Green Post Office", "display_name": "Wrea Green Post Office, Ainsworth Fold, Ribby-with-Wrea, Wrea Green, Preston, Lancashire, England, PR4 2NE, United Kingdom", "boundingbox": ["53.7763797", "53.7764797", "-2.9155193", "-2.9154193"], "geojson": {"type": "Point", "coordinates": [-2.9154693, 53.7764297]}}, {"place_id": 256381923, "licence": "Data \u00a9 OpenStreetMap contributors, ODbL 1.0. http://osm.org/copyright", "osm_type": "node", "osm_id": 4730585816, "lat": "53.7798504", "lon": "-2.9089589", "class": "amenity", "type": "kindergarten", "place_rank": 30, "importance": 5.050659952692481e-05, "addresstype": "amenity", "name": "Wrea Green Pre-School", "display_name": "Wrea Green Pre-School, Wray Crescent, Ribby, Ribby-with-Wrea, Wrea Green, Preston, Lancashire, England, PR4 2WA, United Kingdom", "boundingbox": ["53.7798004", "53.7799004", "-2.9090089", "-2.9089089"], "geojson": {"type": "Point", "coordinates": [-2.9089589, 53.7798504]}}]